ovos_gui/__init__.py
ovos_gui/__main__.py
ovos_gui/bus.py
ovos_gui/constants.py
ovos_gui/extensions.py
ovos_gui/homescreen.py
ovos_gui/namespace.py
ovos_gui/page.py
ovos_gui/service.py
ovos_gui/tui.py
ovos_gui/version.py
ovos_gui/res/gui/qt5/Face.qml
ovos_gui/res/gui/qt5/FeatureRequest.qml
ovos_gui/res/gui/qt5/RequestHandler.qml
ovos_gui/res/gui/qt5/SYSTEM_AnimatedImageFrame.qml
ovos_gui/res/gui/qt5/SYSTEM_Face.qml
ovos_gui/res/gui/qt5/SYSTEM_HtmlFrame.qml
ovos_gui/res/gui/qt5/SYSTEM_ImageFrame.qml
ovos_gui/res/gui/qt5/SYSTEM_Loading.qml
ovos_gui/res/gui/qt5/SYSTEM_Status.qml
ovos_gui/res/gui/qt5/SYSTEM_TextFrame.qml
ovos_gui/res/gui/qt5/SYSTEM_UrlFrame.qml
ovos_gui/res/gui/qt5/SwipeArea.qml
ovos_gui/res/gui/qt5/WebViewHtmlFrame.qml
ovos_gui/res/gui/qt5/WebViewUrlFrame.qml
ovos_gui/res/gui/qt5/animations/loading.json
ovos_gui/res/gui/qt5/animations/status-fail.json
ovos_gui/res/gui/qt5/animations/status-success.json
ovos_gui/res/gui/qt5/face/Eyeball.svg
ovos_gui/res/gui/qt5/face/GreySmile.svg
ovos_gui/res/gui/qt5/face/Smile.svg
ovos_gui/res/gui/qt5/face/lid.svg
ovos_gui/res/gui/qt5/face/upper-lid.svg
ovos_gui-1.3.4.dist-info/licenses/LICENSE.md
ovos_gui-1.3.4.dist-info/METADATA
ovos_gui-1.3.4.dist-info/WHEEL
ovos_gui-1.3.4.dist-info/entry_points.txt
ovos_gui-1.3.4.dist-info/top_level.txt
ovos_gui-1.3.4.dist-info/RECORD
