Metadata-Version: 2.4
Name: ovos_gui
Version: 1.3.4
Summary: ovos-core gui service daemon
Home-page: https://github.com/OpenVoiceOS/ovos-gui
License: Apache-2.0
License-File: LICENSE.md
Requires-Dist: ovos_bus_client<2.0.0,>=1.0.0
Requires-Dist: ovos-utils<1.0.0,>=0.0.37
Requires-Dist: ovos-config<3.0.0,>=0.0.12
Requires-Dist: tornado>=6.0.3,~=6.0
Requires-Dist: ovos-plugin-manager<3.0.0,>=0.5.5
Provides-Extra: extras
Requires-Dist: ovos-gui-plugin-shell-companion<2.0.0,>=1.0.1; extra == "extras"
Dynamic: description
Dynamic: description-content-type
Dynamic: home-page
Dynamic: license
Dynamic: license-file
Dynamic: provides-extra
Dynamic: requires-dist
Dynamic: summary
